{"title": "US pushes for access to iPhones"}
{"title": "New ransomware knows where you live"}
{"title": "'Hack' puts explicit show on US radio"}
{"title": "Martha Lane Fox to join Twitter board"}
{"title": "Uber pays $10m in driver vetting row"}
{"title": "Fallout 4 wins best game at Baftas"}
{"title": "Volvo plans China driverless car tests"}
{"title": "Thai police probe royals Line stickers"}
{"title": "UK hits broadband target… maybe"}
{"title": "Video game Olympics announced for Rio"}
{"title": "The problem with forced tech obsolescence"}
{"title": "Setback for Playboy in hyperlinks case"}
{"title": "Huawei phone uses Leica camera tech"}
{"title": "Tech measures how hard you exercise"}
{"title": "Hands on with the Microsoft Hololens"}
{"title": "A show driven by artificial intelligence"}
{"title": "3D-printed 'Rembrandt' painting"}
{"title": "Fallout 4: Bafta win 'unexpected'"}
{"title": "Doom creator honoured with Bafta"}
{"title": "Batman: Arkham Knight is top British game"}
{"title": "Dara O Briain on Bafta games awards"}
{"title": "Rapture game led pack at Bafta awards"}
{"title": "Can 'pay as you glow' solve Malawi's power crisis?"}
{"title": "Syndicate: I want to stay authentic"}
{"title": "Odd couple"}
{"title": "VR and sport"}
{"title": "Social media blackout"}
{"title": "Is world's greenest office also smart?"}
{"title": "Quantum of menace?"}
{"title": "40 years on"}
{"title": "The eagle that chases drones"}
{"title": "The ship that sails without a crew"}
{"title": "Hydrogen-powered drone takes flight"}
{"title": "Tomorrow's Cities"}
{"title": "Cybersecurity alert"}
{"title": "Video games"}
{"title": "Intelligent Machines"}
{"title": "3D-printed 'Rembrandt' painting"}
{"title": "Fallout 4: Bafta win 'unexpected'"}
{"title": "Doom creator honoured with Bafta"}
{"title": "Batman: Arkham Knight is top British game"}
{"title": "Dara O Briain on Bafta games awards"}
{"title": "Rapture game led pack at Bafta awards"}
